README.md
license
setup.py
deeg/__init__.py
deeg/access.py
deeg/features.py
deeg/models.py
deeg/process.py
deeg/test.py
deeg/utils.py
deeg.egg-info/PKG-INFO
deeg.egg-info/SOURCES.txt
deeg.egg-info/dependency_links.txt
deeg.egg-info/requires.txt
deeg.egg-info/top_level.txt
deeg/models/CNN.py
deeg/models/SST_EmotionNet.py
deeg/models/SVM.py
deeg/models/__init__.py
deeg/models/transformer.py